{
    "$schema": "https://marketplace.umbraco.com/umbraco-marketplace-schema.json",
    "AddOnPackagesRequiredForUmbracoCloud": [],
    "AlternateCategory": "Developer Tools",
    "AuthorDetails": {
      "Name": "Dymior",
      "Description": "Dymior is an innovative startup focused on delivering cutting-edge web solutions that enhance user engagement and streamline data collection. Our mission is to empower businesses and developers with intuitive tools designed for efficiency and responsiveness. By prioritizing automation and user experience, Dymior aims to transform the way organizations interact with their audiences and manage online processes.",
      "Url": "https://github.com/dymior",
      "ImageUrl": "https://github.com/dymior.png"
    },
    "Category": "Editor Tools",
    "Description": "With the Dymior Forms Plugin, web form creation becomes a seamless and efficient process. This versatile plugin empowers users to design and deploy a wide variety of web forms with remarkable speed and intelligence. Whether you're a web developer, marketer, or business owner, Dymior Forms simplifies the task of gathering data and interacting with your audience.",
    "DiscussionForumUrl": "https://github.com/dymior/Dymior-Forms/discussions",
    "DocumentationUrl": "https://github.com/dymior/Dymior-Forms",
    "LicenseTypes": [ "Purchase" ],
    "IssueTrackerUrl": "https://github.com/dymior/Dymior-Forms/issues",
    "IsSubPackageOf": "",
    "PackageType": "Package",
    "PackagesByAuthor": [],
    "RelatedPackages": [
      {
        "GroupTitle": "",
        "PackageId": "",
        "Description": ""
      }
    ],
    "Screenshots": [],
    "Tags": ["Dymior Forms", "Responsive Forms", "Form Builder", "Web Forms", "Form Managment", "Form Submissions"],
    "Title": "Dymior Forms",
    "VersionDependencyMode": "SemVer",
    "VersionSpecificPackageIds": [],
    "VideoUrl": null
  }
